aligni/__init__.py
aligni/api.py
aligni/datatypes.py
aligni/endpoints.py
aligni_python-0.0.1.dist-info/WHEEL
aligni_python-0.0.1.dist-info/METADATA
aligni_python-0.0.1.dist-info/RECORD
