Metadata-Version: 2.1
Name: aligni-python
Version: 0.0.1
Summary: Python library for interfacing to the Aligni (PLM/MRP) API
Home-page: https://mnorman-dev.github.io/aligni-python
License: MIT
Author: Mark Norman
Author-email: mpnorman@gmail.com
Requires-Python: >=3.7.1,<4.0
Classifier: Development Status :: 4 - Beta
Classifier: Intended Audience :: Developers
Classifier: License :: OSI Approved :: MIT License
Classifier: Operating System :: OS Independent
Classifier: Programming Language :: Python
Classifier: Programming Language :: Python :: 3
Classifier: Programming Language :: Python :: 3.10
Classifier: Programming Language :: Python :: 3.7
Classifier: Programming Language :: Python :: 3.8
Classifier: Programming Language :: Python :: 3.9
Classifier: Topic :: Software Development :: Libraries :: Python Modules
Classifier: Typing :: Typed
Requires-Dist: ratelimit (>=2.2)
Requires-Dist: requests (>=2.25)
Project-URL: Documentation, https://mnorman-dev.github.io/aligni-python
Project-URL: Repository, https://github.com/mnorman-dev/aligni-python
